cmus_osx/__init__.py
cmus_osx/constants.py
cmus_osx/env.py
cmus_osx/payload/media_keys.py
cmus_osx/payload/notify.py
cmus_osx/resource/icon.png
cmus_osx/util.py
cmus_osx-3.0.6.dist-info/entry_points.txt
cmus_osx-3.0.6.dist-info/LICENSE
cmus_osx-3.0.6.dist-info/WHEEL
cmus_osx-3.0.6.dist-info/METADATA
cmus_osx-3.0.6.dist-info/RECORD
