Metadata-Version: 2.1
Name: cmus-osx
Version: 3.0.6
Summary: Adds track change notifications, and media key support to cmus.
License: MIT
Author: Philip Trauner
Author-email: philip.trauner@arztpraxis.io
Requires-Python: >=3.7,<4.0
Classifier: License :: OSI Approved :: MIT License
Classifier: Programming Language :: Python :: 3
Classifier: Programming Language :: Python :: 3.7
Classifier: Programming Language :: Python :: 3.8
Requires-Dist: Pillow (>=8.0,<9.0)
Requires-Dist: click (>=7.0,<8.0)
Requires-Dist: mutagen (>=1.42,<2.0)
Requires-Dist: pyobjc (>=6.2,<7.0)
